medallion/__init__.py
medallion/common.py
medallion/exceptions.py
medallion/version.py
medallion/backends/__init__.py
medallion/backends/base.py
medallion/backends/memory_backend.py
medallion/backends/mongodb_backend.py
medallion/filters/__init__.py
medallion/filters/basic_filter.py
medallion/filters/mongodb_filter.py
medallion/scripts/__init__.py
medallion/scripts/run.py
medallion/views/__init__.py
medallion/views/collections.py
medallion/views/discovery.py
medallion/views/manifest.py
medallion/views/objects.py
medallion-3.0.0.dist-info/LICENSE
medallion-3.0.0.dist-info/METADATA
medallion-3.0.0.dist-info/WHEEL
medallion-3.0.0.dist-info/entry_points.txt
medallion-3.0.0.dist-info/top_level.txt
medallion-3.0.0.dist-info/RECORD
