Metadata-Version: 2.1
Name: medallion
Version: 3.0.0
Summary: A TAXII 2.1 Server implementing required endpoints
Home-page: https://oasis-open.github.io/cti-documentation/
Author: OASIS Cyber Threat Intelligence Technical Committee
Author-email: cti-users@lists.oasis-open.org
Maintainer: Emmanuelle Vargas-Gonzalez
Maintainer-email: emmanuelle@mitre.org
License: BSD
Project-URL: Source Code, https://github.com/oasis-open/cti-taxii-server/
Project-URL: Documentation, https://medallion.readthedocs.io/
Project-URL: Bug Tracker, https://github.com/oasis-open/cti-taxii-server/issues/
Keywords: taxii taxii2 server json cti cyber threat intelligence
Platform: UNKNOWN
Classifier: Development Status :: 3 - Alpha
Classifier: Intended Audience :: Developers
Classifier: Topic :: Security
Classifier: License :: OSI Approved :: BSD License
Classifier: Programming Language :: Python :: 3
Classifier: Programming Language :: Python :: 3.5
Classifier: Programming Language :: Python :: 3.6
Classifier: Programming Language :: Python :: 3.7
Classifier: Programming Language :: Python :: 3.8
Requires-Dist: flask (>=0.12.1)
Requires-Dist: Flask-HTTPAuth
Requires-Dist: pytz
Requires-Dist: six
Provides-Extra: docs
Requires-Dist: sphinx ; extra == 'docs'
Requires-Dist: sphinx-prompt ; extra == 'docs'
Provides-Extra: mongo
Requires-Dist: pymongo ; extra == 'mongo'
Provides-Extra: test
Requires-Dist: coverage ; extra == 'test'
Requires-Dist: pytest ; extra == 'test'
Requires-Dist: pytest-cov ; extra == 'test'
Requires-Dist: tox ; extra == 'test'
